buildconfig
