Metadata-Version: 1.0
Name: buildconfig
Version: 0.4
Summary: .buildconfig edit build integration tool
Home-page: https://github.com/mo22/buildconfig
Author: Moritz Möller
Author-email: mm@mxs.de
License: UNKNOWN
Platform: UNKNOWN
